proximity_lock_system/__init__.py
proximity_lock_system/cli.py
proximity_lock_system/config.py
proximity_lock_system/core.py
proximity_lock_system/utils.py
proximity_lock_system-2.1.0.dist-info/LICENSE
proximity_lock_system-2.1.0.dist-info/METADATA
proximity_lock_system-2.1.0.dist-info/WHEEL
proximity_lock_system-2.1.0.dist-info/entry_points.txt
proximity_lock_system-2.1.0.dist-info/top_level.txt
proximity_lock_system-2.1.0.dist-info/RECORD
