Metadata-Version: 2.1
Name: proximity-lock-system
Version: 2.1.0
Summary: Security-style CLI that locks your system when your phone leaves Bluetooth range.
Home-page: https://github.com/Akarshjha03/ProximityLockSystem
Author: Akarsh Jha
Requires-Python: >=3.8
License-File: LICENSE
Requires-Dist: pybluez
